bigtree_api/__init__.py
bigtree_api/models/__init__.py
bigtree_api/models/auth_group.py
bigtree_api/models/auth_permission.py
bigtree_api/models/auth_session.py
bigtree_api/models/auth_user_log.py
bigtree_api/models/base.py
bigtree_api/models/microapp_token.py
bigtree_api/models/sys_book.py
bigtree_api/models/sys_config.py
bigtree_api-0.0.1.dist-info/DESCRIPTION.rst
bigtree_api-0.0.1.dist-info/METADATA
bigtree_api-0.0.1.dist-info/RECORD
bigtree_api-0.0.1.dist-info/WHEEL
bigtree_api-0.0.1.dist-info/metadata.json
bigtree_api-0.0.1.dist-info/top_level.txt
