Metadata-Version: 2.0
Name: bigtree-api
Version: 0.0.1
Summary: bigtree restful api python
Home-page: http://www.hshl.ltd
Author: bigtiger
Author-email: chinafengheping@gmail.com
License: UNKNOWN
Platform: UNKNOWN
Requires-Dist: django-restful (>=0.0.4)
Requires-Dist: requests (>=2.18.4)
